aws_config_checks/__init__.py
aws_config_checks/aws-config-conformance-packs/AWS-Control-Tower-Detective-Guardrails.yaml
aws_config_checks/aws-config-conformance-packs/Operational-Best-Practices-For-NIST-800-181.yaml
aws_config_checks/aws-config-conformance-packs/Operational-Best-Practices-for-ABS-CCIGv2-Material.yaml
aws_config_checks/aws-config-conformance-packs/Operational-Best-Practices-for-ABS-CCIGv2-Standard.yaml
aws_config_checks/aws-config-conformance-packs/Operational-Best-Practices-for-ACSC-Essential8.yaml
aws_config_checks/aws-config-conformance-packs/Operational-Best-Practices-for-ACSC-ISM.yaml
aws_config_checks/aws-config-conformance-packs/Operational-Best-Practices-for-AI-and-ML.yaml
aws_config_checks/aws-config-conformance-packs/Operational-Best-Practices-for-API-Gateway.yaml
aws_config_checks/aws-config-conformance-packs/Operational-Best-Practices-for-APRA-CPG-234.yaml
aws_config_checks/aws-config-conformance-packs/Operational-Best-Practices-for-AWS-Backup.yaml
aws_config_checks/aws-config-conformance-packs/Operational-Best-Practices-for-AWS-Identity-and-Access-Management.yaml
aws_config_checks/aws-config-conformance-packs/Operational-Best-Practices-for-AWS-Well-Architected-Reliability-Pillar.yaml
aws_config_checks/aws-config-conformance-packs/Operational-Best-Practices-for-AWS-Well-Architected-Security-Pillar.yaml
aws_config_checks/aws-config-conformance-packs/Operational-Best-Practices-for-Amazon-DynamoDB-with-Remediation.yaml
aws_config_checks/aws-config-conformance-packs/Operational-Best-Practices-for-Amazon-DynamoDB.yaml
aws_config_checks/aws-config-conformance-packs/Operational-Best-Practices-for-Amazon-S3-with-Remediation.yaml
aws_config_checks/aws-config-conformance-packs/Operational-Best-Practices-for-Amazon-S3.yaml
aws_config_checks/aws-config-conformance-packs/Operational-Best-Practices-for-Asset-Management.yaml
aws_config_checks/aws-config-conformance-packs/Operational-Best-Practices-for-BCP-and-DR.yaml
aws_config_checks-0.0.4.dist-info/METADATA
aws_config_checks-0.0.4.dist-info/WHEEL
aws_config_checks-0.0.4.dist-info/top_level.txt
aws_config_checks-0.0.4.dist-info/RECORD
