Metadata-Version: 2.1
Name: aws-config-checks
Version: 0.0.4
Summary: Provides AWS compliance details
Author-email: "dheeraj.banodha" <dheeraj.banodha@impetus.com>
Classifier: Programming Language :: Python :: 3
Classifier: Operating System :: OS Independent
Requires-Python: >=3.7
